odoo10_addon_product_multi_company-10.0.1.0.0-py2.7-nspkg.pth
odoo/addons/product_multi_company/README.rst
odoo/addons/product_multi_company/__init__.py
odoo/addons/product_multi_company/__manifest__.py
odoo/addons/product_multi_company/hooks.py
odoo/addons/product_multi_company/i18n/es.po
odoo/addons/product_multi_company/i18n/fr.po
odoo/addons/product_multi_company/models/__init__.py
odoo/addons/product_multi_company/models/product_template.py
odoo/addons/product_multi_company/static/description/icon.png
odoo/addons/product_multi_company/tests/__init__.py
odoo/addons/product_multi_company/tests/test_product_multi_company.py
odoo/addons/product_multi_company/views/product_template_view.xml
odoo10_addon_product_multi_company-10.0.1.0.0.dist-info/DESCRIPTION.rst
odoo10_addon_product_multi_company-10.0.1.0.0.dist-info/METADATA
odoo10_addon_product_multi_company-10.0.1.0.0.dist-info/RECORD
odoo10_addon_product_multi_company-10.0.1.0.0.dist-info/WHEEL
odoo10_addon_product_multi_company-10.0.1.0.0.dist-info/metadata.json
odoo10_addon_product_multi_company-10.0.1.0.0.dist-info/namespace_packages.txt
odoo10_addon_product_multi_company-10.0.1.0.0.dist-info/top_level.txt
